qa_pytest_playwright-0.0.13.dist-info/METADATA
qa_pytest_playwright-0.0.13.dist-info/WHEEL
qa_pytest_playwright-0.0.13.dist-info/entry_points.txt
qa_pytest_playwright/__init__.py
qa_pytest_playwright/_version.py
qa_pytest_playwright/logging.ini
qa_pytest_playwright/playwright_configuration.py
qa_pytest_playwright/playwright_steps.py
qa_pytest_playwright/playwright_tests.py
qa_pytest_playwright/playwright_ui_adapter.py
qa_pytest_playwright-0.0.13.dist-info/RECORD
