Metadata-Version: 2.4
Name: qa-pytest-playwright
Version: 0.0.13
Summary: PyTest Playwright library
Author-Email: Adrian Herscu <adrian.herscu@gmail.com>
License-Expression: Apache-2.0
Requires-Python: >=3.13
Requires-Dist: qa-testing-utils
Requires-Dist: qa-pytest-commons
Requires-Dist: tenacity==9.1.2
Requires-Dist: pytest==8.4.1
Requires-Dist: PyHamcrest==2.1.0
Requires-Dist: pyfunctional==1.5.0
Requires-Dist: more-itertools==10.7.0
Requires-Dist: returns==0.25.0
Requires-Dist: playwright==1.57.0
